api_validator/__init__.py
api_validator/version.py
api_validator/bin/__init__.py
api_validator/bin/cli.py
api_validator/bin/logger.py
api_validator/command/__init__.py
api_validator/command/compare.py
api_validator/command/convert.py
api_validator/command/create_config_file.py
api_validator/command/exclude.py
api_validator/command/generate.py
api_validator/command/install.py
api_validator/command/list_jobs.py
api_validator/command/report.py
api_validator/command/report_combined.py
api_validator/command/validate.py
api_validator/command/yolo_traffic.py
api_validator/diff_utils/__init__.py
api_validator/diff_utils/complex_oasdiff_yaml_utils.py
api_validator/diff_utils/config.yml
api_validator/diff_utils/job_summary.md.j2
api_validator/diff_utils/job_summary.py
api_validator/diff_utils/jobs.py
api_validator/diff_utils/oasdiff_utils.py
api_validator/oasdiff_v2/__init__.py
api_validator/oasdiff_v2/compare.py
api_validator/oasdiff_v2/diff_data.py
api_validator/oasdiff_v2/missing_parameters_utils.py
api_validator/oasdiff_v2/param_report.md.j2
api_validator/oasdiff_v2/param_report.py
api_validator/oasdiff_v2/parse.py
api_validator/oasdiff_v2/parameters/__init__.py
api_validator/oasdiff_v2/parameters/added_parameter_data.py
api_validator/oasdiff_v2/parameters/added_request_body_parameters.py
api_validator/oasdiff_v2/parameters/deleted_parameter_data.py
api_validator/oasdiff_v2/parameters/deleted_request_body_parameters.py
api_validator/oasdiff_v2/parameters/modified_parameters.py
api_validator/oasdiff_v2/parameters/modified_request_body_parameters.py
api_validator/oasdiff_v2/parameters/parameter_data.py
api_validator/oasdiff_v2/parameters/request_body_data.py
api_validator/oasdiff_v2/parameters/request_body_parameters.py
api_validator/oasdiff_v2/parameters/security_requirements.py
api_validator/shared/__init__.py
api_validator/shared/click_validators.py
api_validator/swagger_gen/__init__.py
api_validator/swagger_gen/api_extractor.py
api_validator/tests/__init__.py
api_validator-0.3.15.dist-info/METADATA
api_validator-0.3.15.dist-info/WHEEL
api_validator-0.3.15.dist-info/entry_points.txt
api_validator-0.3.15.dist-info/top_level.txt
api_validator-0.3.15.dist-info/zip-safe
api_validator-0.3.15.dist-info/RECORD
