Metadata-Version: 2.1
Name: api-validator
Version: 0.3.15
Summary: Validate OpenAPI specs by sending traffic
Home-page: https://github.com/nvsecurity/api-validator
Author: Kinnaird McQuade
Author-email: kinnaird@nightvision.net
Keywords: openapi
Classifier: Programming Language :: Python :: 3
Classifier: Operating System :: OS Independent
Requires-Python: >=3.11
Requires-Dist: click
Requires-Dist: click-option-group
Requires-Dist: invoke
Requires-Dist: loguru
Requires-Dist: PyYAML
Requires-Dist: Jinja2
Requires-Dist: pandas
Requires-Dist: requests
Requires-Dist: python-dotenv
